barret/src/barret.v
//Made by: Aldo Balsamo

//Barret Reduction for prime finite fields
//k = 2
 /*

    Calculate q=⌊x/2k⌋.
    Calculate q′=q⋅μ.
    Calculate q′′=⌊q′/2k⌋.
    Compute r=x−q′′⋅m

*/

//Input: Positive integers x < 2^2k , 2^k−1 < q < 2^k
//<------------------------TEST: WORKING WITH GF(3)---------------------->
module barret(
    input clk,
    input wire [3:0] din_a,
    //the operation coming to din_a is a result of addition, substraction or multiplication
    //therefore it can be as large as log_2(a*b) = log_2(a) + log_2(b)
    input wire [3:0]din_m, //temporal, might set it on stone and just modify it
    //when generating the code
    output wire [1:0] dout_r//result must be at most 2 bit long
);

//μ value because depends only on m and not on x. 
//Since μ=⌊2^2k/m​⌋, it remains constant as long as 
//m does not change. important 
//This precalculation significantly speeds up the reduction process.

wire [3:0] mu_constant = 5; //⌊2^2k/m​⌋ where m is 3 and k is 2 
wire [3:0] q_val;
assign q_val = din_a >> 2; //⌊din_a/2^k​⌋ since our divisor is
                             //a power of two we can just shift right

wire[3:0] q_hat;
assign q_hat = q_val * mu_constant;

wire [3:0] t_val;
assign t_val = q_hat >> 2;//⌊q_hat/2^k​⌋

wire[3:0] mult;
assign mult = t_val * din_m;
wire[3:0] result;
assign result = din_a - mult;

wire[3:0] test; 

assign test = din_a - (((q_val*mu_constant) >> 2) * din_m);

assign dout_r = test >= din_m ? test - 3 : test;


endmodule

barret/src/waveform.vcd
$version Generated by VerilatedVcd $end
$date Thu Feb 29 00:07:29 2024
 $end
$timescale   1ps $end

 $scope module TOP $end
  $var wire  1 # clk $end
  $var wire  4 $ din_a [3:0] $end
  $var wire  4 % din_m [3:0] $end
  $var wire  2 & dout_r [1:0] $end
  $scope module barret $end
   $var wire  1 # clk $end
   $var wire  4 $ din_a [3:0] $end
   $var wire  4 % din_m [3:0] $end
   $var wire  2 & dout_r [1:0] $end
   $var wire  4 - mu_constant [3:0] $end
   $var wire  4 * mult [3:0] $end
   $var wire  4 ( q_hat [3:0] $end
   $var wire  4 ' q_val [3:0] $end
   $var wire  4 + result [3:0] $end
   $var wire  4 ) t_val [3:0] $end
   $var wire  4 , test [3:0] $end
  $upscope $end
 $upscope $end
$enddefinitions $end


#0
1#
b0000 $
b0011 %
b00 &
b0000 '
b0000 (
b0000 )
b0000 *
b0000 +
b0000 ,
b0101 -
#1
0#
#2
1#
b0001 $
b01 &
b0001 +
b0001 ,
#3
0#
#4
1#
b0010 $
b10 &
b0010 +
b0010 ,
#5
0#
#6
1#
b0011 $
b00 &
b0011 +
b0011 ,
#7
0#
#8
1#
b0100 $
b01 &
b0001 '
b0101 (
b0001 )
b0011 *
b0001 +
b0001 ,
#9
0#
#10
1#
b0101 $
b10 &
b0010 +
b0010 ,
#11
0#
#12
1#
b0110 $
b00 &
b0011 +
b0011 ,
#13
0#
#14
1#
b0111 $
b01 &
b0100 +
b0100 ,
#15
0#
#16
1#
b1000 $
b10 &
b0010 '
b1010 (
b0010 )
b0110 *
b0010 +
b0010 ,
#17
0#
#18
1#
b1001 $
b00 &
b0011 +
b0011 ,
#19
0#
#20
1#
b1010 $
b01 &
b0100 +
b0100 ,
#21
0#
#22
1#
b1011 $
b10 &
b0101 +
b0101 ,
#23
0#
#24
1#
b1100 $
b00 &
b0011 '
b1111 (
b0011 )
b1001 *
b0011 +
b0011 ,
#25
0#
#26
1#
b1101 $
b01 &
b0100 +
b0100 ,
#27
0#
#28
1#
b1110 $
b10 &
b0101 +
b0101 ,
